LICENSE.txt
MANIFEST.in
README.md
setup.cfg
setup.py
qgprofiler/__init__.py
qgprofiler/constants.py
qgprofiler/helper.py
qgprofiler/node.py
qgprofiler/qg_profile_aggregator.py
qgprofiler/qg_profiler.py
qgprofiler.egg-info/PKG-INFO
qgprofiler.egg-info/SOURCES.txt
qgprofiler.egg-info/dependency_links.txt
qgprofiler.egg-info/not-zip-safe
qgprofiler.egg-info/top_level.txt
qgprofiler/templates/html1.txt
qgprofiler/templates/html2.txt