Metadata-Version: 1.1
Name: qgprofiler
Version: 0.1.13
Summary: Profiler with time deterministic profiling of functions
Home-page: https://github.com/quantumgraph/qgprofiler
Author: QuantumGraph
Author-email: contact@quantumgraph.com
License: MIT
Keywords: profiler,monitoring,logging,utility
Platform: UNKNOWN
Classifier: Development Status :: 4 - Beta
Classifier: Topic :: Utilities
Classifier: License :: Freeware
Classifier: Programming Language :: Python
